{
    "display" : {
        "icon" : {
            "item" : "pixelmon:pixelmon_sprite",
            "nbt" : "{\"SpriteName\":\"pixelmon:sprites/pokemon/490\"}"
        },
        "title" : {
            "translate" : "advancements.manaphy_capture.title"
        },
        "description" : {
            "translate" : "advancements.manaphy_capture.description"
        },
        "hidden": true
    },
    "parent" : "pixelmon:legendaries/legendary_capture_trigger",
    "criteria" : {
        "manaphy_capture" : {
            "trigger" : "pixelmon:legendary_capture_trigger",
            "conditions" : {
                "pokemon" : "manaphy"
            }
        }
    }
}